{"lastUsed":1650068215371,"path":"C:\/Users\/erend\/Desktop\/Github Projeleri\/AWS-Java-Servlet-Project","projectCount":1,"recentFiles":[{"path":"\/Proje","parentWorkspace":"C:\/Users\/erend\/Desktop\/Proje","name":"pom.xml","lastModified":1650068233909,"locationURI":"file:\/C:\/Users\/erend\/Desktop\/Proje\/Proje\/pom.xml"},{"path":"\/Proje\/src\/main\/java\/net\/codejava\/aws","parentWorkspace":"C:\/Users\/erend\/Desktop\/Proje","name":"HomeServlet.java","lastModified":1650068237467,"locationURI":"file:\/C:\/Users\/erend\/Desktop\/Proje\/Proje\/src\/main\/java\/net\/codejava\/aws\/HomeServlet.java"},{"path":"\/Proje\/src\/main\/webapp","parentWorkspace":"C:\/Users\/erend\/Desktop\/Proje","name":"message.jsp","lastModified":1649876507675,"locationURI":"file:\/C:\/Users\/erend\/Desktop\/Proje\/Proje\/src\/main\/webapp\/message.jsp"},{"path":"\/Proje\/src\/main\/java\/net\/codejava\/aws","parentWorkspace":"C:\/Users\/erend\/Desktop\/Proje","name":"S3Util.java","lastModified":1650068237467,"locationURI":"file:\/C:\/Users\/erend\/Desktop\/Proje\/Proje\/src\/main\/java\/net\/codejava\/aws\/S3Util.java"},{"path":"\/Proje\/src\/main\/webapp","parentWorkspace":"C:\/Users\/erend\/Desktop\/Proje","name":"upload.jsp","lastModified":1650063865033,"locationURI":"file:\/C:\/Users\/erend\/Desktop\/Proje\/Proje\/src\/main\/webapp\/upload.jsp"},{"path":"\/Proje\/src\/main\/java\/net\/codejava\/aws","parentWorkspace":"C:\/Users\/erend\/Desktop\/Proje","name":"FileUploadServlet.java","lastModified":1650068237467,"locationURI":"file:\/C:\/Users\/erend\/Desktop\/Proje\/Proje\/src\/main\/java\/net\/codejava\/aws\/FileUploadServlet.java"}]}